provchain/__init__.py
provchain/__main__.py
provchain/config.py
provchain/cli/__init__.py
provchain/cli/main.py
provchain/cli/commands/__init__.py
provchain/cli/commands/attack.py
provchain/cli/commands/config.py
provchain/cli/commands/sbom.py
provchain/cli/commands/verify.py
provchain/cli/commands/vet.py
provchain/cli/commands/vuln.py
provchain/cli/commands/watch.py
provchain/cli/formatters/__init__.py
provchain/cli/formatters/json.py
provchain/cli/formatters/markdown.py
provchain/cli/formatters/sarif.py
provchain/cli/formatters/table.py
provchain/core/__init__.py
provchain/core/package.py
provchain/core/sbom.py
provchain/core/version.py
provchain/data/__init__.py
provchain/data/cache.py
provchain/data/db.py
provchain/data/models.py
provchain/integrations/__init__.py
provchain/integrations/attack_feeds.py
provchain/integrations/github.py
provchain/integrations/gitlab.py
provchain/integrations/osv.py
provchain/integrations/pypi.py
provchain/interrogator/__init__.py
provchain/interrogator/cvss.py
provchain/interrogator/engine.py
provchain/interrogator/risk_scorer.py
provchain/interrogator/analyzers/__init__.py
provchain/interrogator/analyzers/attack.py
provchain/interrogator/analyzers/base.py
provchain/interrogator/analyzers/behavior.py
provchain/interrogator/analyzers/install_hooks.py
provchain/interrogator/analyzers/maintainer.py
provchain/interrogator/analyzers/metadata.py
provchain/interrogator/analyzers/typosquat.py
provchain/interrogator/analyzers/vulnerability.py
provchain/interrogator/sandbox/__init__.py
provchain/interrogator/sandbox/container.py
provchain/interrogator/sandbox/tracer.py
provchain/plugins/__init__.py
provchain/plugins/interface.py
provchain/plugins/loader.py
provchain/utils/__init__.py
provchain/utils/hashing.py
provchain/utils/logging.py
provchain/utils/network.py
provchain/verifier/__init__.py
provchain/verifier/engine.py
provchain/verifier/provenance/__init__.py
provchain/verifier/provenance/gpg.py
provchain/verifier/provenance/hash.py
provchain-1.1.3.dist-info/licenses/LICENSE
provchain-1.1.3.dist-info/METADATA
provchain-1.1.3.dist-info/WHEEL
provchain-1.1.3.dist-info/entry_points.txt
provchain-1.1.3.dist-info/top_level.txt
provchain-1.1.3.dist-info/RECORD
