Metadata-Version: 2.4
Name: provchain
Version: 1.1.3
Summary: Supply chain security platform with behavioral analysis and provenance verification
Author: Icarus Protection Firm
License: Apache-2.0
Project-URL: Homepage, https://github.com/ipf/provchain
Project-URL: Documentation, https://provchain.readthedocs.io
Project-URL: Repository, https://github.com/ipf/provchain
Project-URL: Issues, https://github.com/ipf/provchain/issues
Keywords: security,supply-chain,dependencies,vulnerability,provenance
Classifier: Development Status :: 4 - Beta
Classifier: Intended Audience :: Developers
Classifier: License :: OSI Approved :: Apache Software License
Classifier: Programming Language :: Python :: 3
Classifier: Programming Language :: Python :: 3.10
Classifier: Programming Language :: Python :: 3.11
Classifier: Programming Language :: Python :: 3.12
Classifier: Topic :: Security
Classifier: Topic :: Software Development :: Libraries :: Python Modules
Requires-Python: >=3.10
License-File: LICENSE
Requires-Dist: typer>=0.9.0
Requires-Dist: rich>=13.0.0
Requires-Dist: httpx>=0.25.0
Requires-Dist: pydantic>=2.0.0
Requires-Dist: sqlalchemy>=2.0.0
Requires-Dist: packaging>=23.0
Requires-Dist: tomli>=2.0.0; python_version < "3.11"
Requires-Dist: tomli-w>=1.0.0
Requires-Dist: build>=0.10.0
Provides-Extra: behavioral
Requires-Dist: docker>=6.0.0; extra == "behavioral"
Provides-Extra: dev
Requires-Dist: pytest>=7.0.0; extra == "dev"
Requires-Dist: pytest-cov>=4.0.0; extra == "dev"
Requires-Dist: pytest-asyncio>=0.21.0; extra == "dev"
Requires-Dist: ruff>=0.1.0; extra == "dev"
Requires-Dist: mypy>=1.0.0; extra == "dev"
Requires-Dist: hypothesis>=6.0.0; extra == "dev"
Requires-Dist: bandit>=1.7.0; extra == "dev"
Dynamic: license-file
